hydralink/__init__.py
hydralink/__main__.py
hydralink/bcm89881.py
hydralink/gui.py
hydralink/hydralink.py
hydralink/lan7801.py
hydralink/lan7801_libusb.py
hydralink/lan7801_win.py
hydralink/windows_apis.py
hydralink-0.2.9.dist-info/LICENSE
hydralink-0.2.9.dist-info/METADATA
hydralink-0.2.9.dist-info/WHEEL
hydralink-0.2.9.dist-info/entry_points.txt
hydralink-0.2.9.dist-info/top_level.txt
hydralink-0.2.9.dist-info/RECORD
