Metadata-Version: 2.1
Name: hydralink
Version: 0.2.9
Summary: Library to configure the dissecto hydralink
Author: Enrico POZZOBON
Classifier: Programming Language :: Python :: 3
Classifier: Programming Language :: Python :: 3 :: Only
Classifier: Programming Language :: Python :: 3.11
Classifier: Programming Language :: Python :: 3.12
Requires-Python: <4,>=3.11
License-File: LICENSE
Requires-Dist: pyusb
